{
  "aor": 0.0048575499999999995,
  "aqi": 0.00563777505,
  "bids_meta": {
    "EchoTime": 0.028,
    "RepetitionTime": 2.0,
    "TaskName": "Main",
    "dataset": "ds002797",
    "modality": "bold",
    "run_id": 9,
    "subject_id": "27",
    "task_id": "Main"
  },
  "dummy_trs": 2,
  "dvars_nstd": 17.31847060045226,
  "dvars_std": 1.1015571592964823,
  "dvars_vstd": 1.0175376694472362,
  "efc": 0.5180634157802465,
  "fber": 16495.888671875,
  "fd_mean": 0.12866545998265647,
  "fd_num": 23,
  "fd_perc": 11.5,
  "fwhm_avg": 2.655507830960687,
  "fwhm_x": 2.4482133333333334,
  "fwhm_y": 2.8559466666666666,
  "fwhm_z": 2.6623634928820614,
  "gcor": 0.0256082,
  "gsr_x": 0.0008976788958534598,
  "gsr_y": 0.024927187711000443,
  "provenance": {
    "md5sum": "759a917e2edc9d82bc7be70f48914c0d",
    "settings": {
      "fd_thres": 0.2,
      "testing": false
    },
    "software": "mriqc",
    "version": "22.0.6",
    "webapi_port": null,
    "webapi_url": "https://mriqc.nimh.nih.gov/api/v1"
  },
  "size_t": 200,
  "size_x": 64,
  "size_y": 64,
  "size_z": 42,
  "snr": 6.202018764662599,
  "spacing_tr": 2.0,
  "spacing_x": 3.0,
  "spacing_y": 3.0,
  "spacing_z": 3.0000035762786865,
  "summary_bg_k": 21.139785020805505,
  "summary_bg_mad": 50.734647606199374,
  "summary_bg_mean": 156.21914672851562,
  "summary_bg_median": 38.44499969482422,
  "summary_bg_n": 98627.0,
  "summary_bg_p05": 1.274999976158142,
  "summary_bg_p95": 747.8019897460937,
  "summary_bg_stdv": 327.0252380371094,
  "summary_fg_k": 0.8456582129989476,
  "summary_fg_mad": 712.5460102678103,
  "summary_fg_mean": 4784.0966796875,
  "summary_fg_median": 4774.0048828125,
  "summary_fg_n": 37207.0,
  "summary_fg_p05": 3533.29091796875,
  "summary_fg_p95": 6046.770361328125,
  "summary_fg_stdv": 769.7398071289062,
  "tsnr": 69.75395317887887
}